rdsmon/__init__.py
rdsmon/client.py
rdsmon/commandline.py
rdsmon/configuration.py
rdsmon/const.py
rdsmon/main.py
rdsmon-0.1.0.dist-info/LICENSE
rdsmon-0.1.0.dist-info/METADATA
rdsmon-0.1.0.dist-info/WHEEL
rdsmon-0.1.0.dist-info/RECORD
