Metadata-Version: 2.1
Name: rdsmon
Version: 0.1.0
Summary: python CLI for monitoring metrics of amazon RDS instances
License: Apache 2.0
Author: symonk
Author-email: jackofspaces@gmail.com
Requires-Python: >=3.8,<4.0
Classifier: License :: Other/Proprietary License
Classifier: Programming Language :: Python :: 3
Classifier: Programming Language :: Python :: 3.8
Classifier: Programming Language :: Python :: 3.9
Classifier: Programming Language :: Python :: 3.10
Classifier: Programming Language :: Python :: 3.11
Requires-Dist: boto3 (>=1.28.53,<2.0.0)
Requires-Dist: loguru (>=0.7.2,<0.8.0)
Requires-Dist: typer (>=0.9.0,<0.10.0)
